speech2spikes.py
speech2spikes-1.0.1.dist-info/LICENSE
speech2spikes-1.0.1.dist-info/METADATA
speech2spikes-1.0.1.dist-info/WHEEL
speech2spikes-1.0.1.dist-info/RECORD
