Metadata-Version: 2.1
Name: speech2spikes
Version: 1.0.1
Summary: Speech2Spikes: Efficient Audio Encoding Pipeline for Real-time Neuromorphic Systems
Home-page: https://github.com/Accenture/speech2spikes
License: Proprietary
Author: Noah Pacik-Nelson
Author-email: noah.pacik-nelson@accenture.com
Requires-Python: >=3.10,<4.0
Classifier: License :: Other/Proprietary License
Classifier: Programming Language :: Python :: 3
Classifier: Programming Language :: Python :: 3.10
Classifier: Programming Language :: Python :: 3.11
Requires-Dist: torch (>=2.0.1,<3.0.0)
Requires-Dist: torchaudio (>=2.0.2,<3.0.0)
